ovos_solver_openai_persona/__init__.py
ovos_solver_openai_persona/dialog_transformers.py
ovos_solver_openai_persona/engines.py
ovos_solver_openai_persona/summarizer.py
ovos_solver_openai_persona/version.py
ovos_solver_openai_persona_plugin-1.2.0.dist-info/LICENSE
ovos_solver_openai_persona_plugin-1.2.0.dist-info/METADATA
ovos_solver_openai_persona_plugin-1.2.0.dist-info/WHEEL
ovos_solver_openai_persona_plugin-1.2.0.dist-info/entry_points.txt
ovos_solver_openai_persona_plugin-1.2.0.dist-info/top_level.txt
ovos_solver_openai_persona_plugin-1.2.0.dist-info/zip-safe
ovos_solver_openai_persona_plugin-1.2.0.dist-info/RECORD
