Metadata-Version: 2.1
Name: ovos-solver-openai-persona-plugin
Version: 1.2.0
Summary: A question solver plugin for ovos
Home-page: https://github.com/OpenVoiceOS/ovos-solver-plugin-openai-persona
Author: jarbasai
Author-email: jarbasai@mailfence.com
License: MIT
Keywords: ovos plugin utterance fallback query
License-File: LICENSE
Requires-Dist: requests
Requires-Dist: ovos-plugin-manager<1.0.0,>=0.0.26
